renogy_ble/__init__.py
renogy_ble/ble.py
renogy_ble/parser.py
renogy_ble/register_map.py
renogy_ble/renogy_parser.py
renogy_ble-1.2.0.dist-info/METADATA
renogy_ble-1.2.0.dist-info/WHEEL
renogy_ble-1.2.0.dist-info/licenses/LICENSE
renogy_ble-1.2.0.dist-info/RECORD
