Metadata-Version: 2.4
Name: renogy-ble
Version: 1.2.0
Summary: A library for parsing Renogy BLE data
Project-URL: Homepage, https://github.com/IAmTheMitchell/renogy-ble
Project-URL: Bug Tracker, https://github.com/IAmTheMitchell/renogy-ble/issues
Project-URL: Changelog, https://github.com/IAmTheMitchell/renogy-ble/blob/main/CHANGELOG.md
Author-email: Mitchell Carlson <mitchell.carlson.pro@gmail.com>
License-Expression: Apache-2.0
License-File: LICENSE
Classifier: Operating System :: OS Independent
Classifier: Programming Language :: Python :: 3
Requires-Python: >=3.11
Requires-Dist: bleak-retry-connector>=4.4.3
Requires-Dist: bleak>=1.0.1
